graph2sound/__init__.py
graph2sound-1.1.4.dist-info/LICENSE
graph2sound-1.1.4.dist-info/METADATA
graph2sound-1.1.4.dist-info/WHEEL
graph2sound-1.1.4.dist-info/top_level.txt
graph2sound-1.1.4.dist-info/RECORD
