Metadata-Version: 2.1
Name: graph2sound
Version: 1.1.4
Summary: Read the latest Real Python tutorials
Author: Crossed Omega
License: MIT License
Project-URL: Homepage, https://gitlab.com/p8244/graph2sound
Classifier: License :: OSI Approved :: MIT License
Classifier: Programming Language :: Python
Classifier: Programming Language :: Python :: 3
Requires-Python: >=3.6
License-File: LICENSE
Requires-Dist: numpy >=2.0.0
Requires-Dist: scipy >=1.14.0
Requires-Dist: sounddevice >=0.4.7
